vaex/contrib/__init__.py
vaex/contrib/_version.py
vaex/contrib/io/__init__.py
vaex/contrib/io/gbq.py
vaex/contrib/io/gbq_test.py
vaex_contrib-0.1.3.dist-info/LICENSE.txt
vaex_contrib-0.1.3.dist-info/METADATA
vaex_contrib-0.1.3.dist-info/WHEEL
vaex_contrib-0.1.3.dist-info/top_level.txt
vaex_contrib-0.1.3.dist-info/RECORD
